odoo/addons/sale_order_line_date/README.rst
odoo/addons/sale_order_line_date/__init__.py
odoo/addons/sale_order_line_date/__manifest__.py
odoo/addons/sale_order_line_date/i18n/ca.po
odoo/addons/sale_order_line_date/i18n/de.po
odoo/addons/sale_order_line_date/i18n/el_GR.po
odoo/addons/sale_order_line_date/i18n/es.po
odoo/addons/sale_order_line_date/i18n/es_ES.po
odoo/addons/sale_order_line_date/i18n/es_VE.po
odoo/addons/sale_order_line_date/i18n/fi.po
odoo/addons/sale_order_line_date/i18n/fr.po
odoo/addons/sale_order_line_date/i18n/hr.po
odoo/addons/sale_order_line_date/i18n/hr_HR.po
odoo/addons/sale_order_line_date/i18n/hu.po
odoo/addons/sale_order_line_date/i18n/it.po
odoo/addons/sale_order_line_date/i18n/nl.po
odoo/addons/sale_order_line_date/i18n/nl_NL.po
odoo/addons/sale_order_line_date/i18n/pt.po
odoo/addons/sale_order_line_date/i18n/pt_BR.po
odoo/addons/sale_order_line_date/i18n/ro.po
odoo/addons/sale_order_line_date/i18n/sale_order_line_date.pot
odoo/addons/sale_order_line_date/i18n/sk.po
odoo/addons/sale_order_line_date/i18n/sl.po
odoo/addons/sale_order_line_date/i18n/tr.po
odoo/addons/sale_order_line_date/i18n/tr_TR.po
odoo/addons/sale_order_line_date/i18n/vi_VN.po
odoo/addons/sale_order_line_date/i18n/zh_CN.po
odoo/addons/sale_order_line_date/models/__init__.py
odoo/addons/sale_order_line_date/models/sale_order.py
odoo/addons/sale_order_line_date/models/sale_order_line.py
odoo/addons/sale_order_line_date/readme/CONTRIBUTORS.md
odoo/addons/sale_order_line_date/readme/CREDITS.md
odoo/addons/sale_order_line_date/readme/DESCRIPTION.md
odoo/addons/sale_order_line_date/readme/USAGE.md
odoo/addons/sale_order_line_date/reports/sale_order_report.xml
odoo/addons/sale_order_line_date/static/description/icon.png
odoo/addons/sale_order_line_date/static/description/index.html
odoo/addons/sale_order_line_date/static/src/js/sale_order_line_field/sale_order_line_field.esm.js
odoo/addons/sale_order_line_date/tests/__init__.py
odoo_addon_sale_order_line_date-19.0.1.0.0.3.dist-info/METADATA
odoo_addon_sale_order_line_date-19.0.1.0.0.3.dist-info/WHEEL
odoo_addon_sale_order_line_date-19.0.1.0.0.3.dist-info/top_level.txt
odoo_addon_sale_order_line_date-19.0.1.0.0.3.dist-info/RECORD
