Metadata-Version: 2.1
Name: odoo-addon-sale_order_line_date
Version: 19.0.1.0.0.3
Requires-Dist: odoo==19.0.*
Summary: Adds a commitment date to each sale order line.
Home-page: https://github.com/OCA/sale-workflow
License: AGPL-3
Author: OdooMRP team,AvanzOSC,Serv. Tecnol. Avanzados - Pedro M. Baeza,Odoo Community Association (OCA), SprintIT Ltd.
Author-email: support@odoo-community.org
Classifier: Programming Language :: Python
Classifier: Framework :: Odoo
Classifier: Framework :: Odoo :: 19.0
Classifier: License :: OSI Approved :: GNU Affero General Public License v3
